{
  "name": "r2k-real-estate",
  "description": "Russell 2000 Real Estate (98 companies)",
  "tickers": [
    "CTRE",
    "AHR",
    "EPRT",
    "TRNO",
    "RHP",
    "KRG",
    "COMP",
    "SBRA",
    "MAC",
    "PECO",
    "NHI",
    "OUT",
    "SKT",
    "IRT",
    "BNL",
    "CDP",
    "LXP",
    "SLG",
    "APLE",
    "UE",
    "AKR",
    "JOE",
    "FCPT",
    "IVT",
    "CURB",
    "NMRK",
    "DRH",
    "GNL",
    "GTY",
    "LTC",
    "CWK",
    "SHO",
    "NTST",
    "DHC",
    "IIPR",
    "PEB",
    "VRE",
    "XHR",
    "SILA",
    "KW",
    "DEI",
    "UMH",
    "RLJ",
    "SMA",
    "AAT",
    "CSR",
    "DEA",
    "JBGS",
    "PDM",
    "SAFE",
    "PKST",
    "WSR",
    "ESRT",
    "CBL",
    "MMI",
    "NXRT",
    "CTO",
    "UHT",
    "EXPI",
    "GOOD",
    "ALX",
    "BDN",
    "FOR",
    "AHRT",
    "FPI",
    "INN",
    "CHCT",
    "XRN",
    "PSTL",
    "OLP",
    "TRC",
    "LAND",
    "BFS",
    "CLDT",
    "ILPT",
    "SVC",
    "HPP",
    "FVR",
    "REAX",
    "SITC",
    "RMR",
    "FRPH",
    "PINE",
    "NLOP",
    "STRS",
    "NXDT",
    "BRT",
    "SEG",
    "BHR",
    "DOUG",
    "MDV",
    "RMAX",
    "MLP",
    "STRW",
    "TCI",
    "FSP",
    "CLPR",
    "ARL"
  ],
  "pairs": [
    [
      "CTRE",
      "AHR"
    ],
    [
      "EPRT",
      "TRNO"
    ],
    [
      "RHP",
      "KRG"
    ],
    [
      "COMP",
      "SBRA"
    ],
    [
      "MAC",
      "PECO"
    ],
    [
      "NHI",
      "OUT"
    ],
    [
      "SKT",
      "IRT"
    ],
    [
      "BNL",
      "CDP"
    ],
    [
      "LXP",
      "SLG"
    ],
    [
      "APLE",
      "UE"
    ],
    [
      "AKR",
      "JOE"
    ],
    [
      "FCPT",
      "IVT"
    ],
    [
      "CURB",
      "NMRK"
    ],
    [
      "DRH",
      "GNL"
    ],
    [
      "GTY",
      "LTC"
    ],
    [
      "CWK",
      "SHO"
    ],
    [
      "NTST",
      "DHC"
    ],
    [
      "IIPR",
      "PEB"
    ],
    [
      "VRE",
      "XHR"
    ],
    [
      "SILA",
      "KW"
    ],
    [
      "DEI",
      "UMH"
    ],
    [
      "RLJ",
      "SMA"
    ],
    [
      "AAT",
      "CSR"
    ],
    [
      "DEA",
      "JBGS"
    ],
    [
      "PDM",
      "SAFE"
    ],
    [
      "PKST",
      "WSR"
    ],
    [
      "ESRT",
      "CBL"
    ],
    [
      "MMI",
      "NXRT"
    ],
    [
      "CTO",
      "UHT"
    ],
    [
      "EXPI",
      "GOOD"
    ],
    [
      "ALX",
      "BDN"
    ],
    [
      "FOR",
      "AHRT"
    ],
    [
      "FPI",
      "INN"
    ],
    [
      "CHCT",
      "XRN"
    ],
    [
      "PSTL",
      "OLP"
    ],
    [
      "TRC",
      "LAND"
    ],
    [
      "BFS",
      "CLDT"
    ],
    [
      "ILPT",
      "SVC"
    ],
    [
      "HPP",
      "FVR"
    ],
    [
      "REAX",
      "SITC"
    ],
    [
      "RMR",
      "FRPH"
    ],
    [
      "PINE",
      "NLOP"
    ],
    [
      "STRS",
      "NXDT"
    ],
    [
      "BRT",
      "SEG"
    ],
    [
      "BHR",
      "DOUG"
    ],
    [
      "MDV",
      "RMAX"
    ],
    [
      "MLP",
      "STRW"
    ],
    [
      "TCI",
      "FSP"
    ],
    [
      "CLPR",
      "ARL"
    ]
  ],
  "sector": "Real Estate",
  "vol_driver": "Russell 2000 Real Estate \u2014 small-cap sector fundamentals",
  "source": "iShares Russell 2000 ETF (IWM) holdings"
}